live_coder/__init__.py
live_coder/__main__.py
live_coder/_add_execution_prints.py
live_coder/_add_prints.py
live_coder/_built_in_methods.py
live_coder/_call_id_to_function.py
live_coder/_change_block_classes.py
live_coder/_change_classes.py
live_coder/_constants.py
live_coder/_debug.py
live_coder/_find_tests.py
live_coder/_function_output_objects.py
live_coder/_get_change_lines.py
live_coder/_get_change_objects.py
live_coder/_get_change_values.py
live_coder/_get_executed_functions.py
live_coder/_get_variables.py
live_coder/_html_for_print_output.py
live_coder/_output_objects.py
live_coder/_parse_import.py
live_coder/_pick_test_class.py
live_coder/_print_adder.py
live_coder/_print_to_vars.py
live_coder/_project_files_finder.py
live_coder/_render_executed_functions.py
live_coder/_run_code.py
live_coder/_run_test.py
live_coder/_string_tools.py
live_coder/_test_class.py
live_coder/_testing_code_file.py
live_coder/_tokenize_python.py
live_coder/_un_nest_functions.py
live_coder/_update_print_references.py
live_coder/server.py
live_coder-1.0.2.dist-info/METADATA
live_coder-1.0.2.dist-info/WHEEL
live_coder-1.0.2.dist-info/top_level.txt
live_coder-1.0.2.dist-info/RECORD
