Metadata-Version: 2.1
Name: live-coder
Version: 1.0.2
Summary: Server for Live Coder, works with the Live Coder VSCode extension.
Home-page: https://gitlab.com/Fraser-Greenlee/live-coding/tree/server
Author: Fraser Greenlee
Author-email: frassyg@gmail.com
License: UNKNOWN
Platform: UNKNOWN
Classifier: Programming Language :: Python :: 3
Classifier: Operating System :: OS Independent
Requires-Dist: astor (==0.8.0)
Requires-Dist: flask (==1.0.2)
Requires-Dist: yapf (==0.27.0)
Requires-Dist: pygments (==2.4.2)
